Workbook

Sheet Movimentação
A1: Entrada/Saída | B1: Data | C1: Data | D1: Movimentação | E1: Produto | F1: Instituição | G1: Quantidade | H1: Preço unitário | I1: Valor da Operação
A2: Debito | B2: 05/06/2026 | C2: 46178 | D2: RESGATE ANTECIPADO/ | E2: CDB - CDB526CSFDK - BANCO DO BRASIL S/A | F2: BANCO DO BRASIL S/A | G2: 8000 | H2: 0.01000064 | I2: 80.01
A3: Debito | B3: 02/06/2026 | C3: 46175 | D3: Direitos de Subscrição - Não Exercido | E3: AFHI12 - AF INVEST CRI FDO. INV. IMOB - RECEBÍVEIS IMOB. | F3: XP INVESTIMENTOS CCTVM S/A | G3: 0 | H3: - | I3: -
A4: Credito | B4: 01/06/2026 | C4: 46174 | D4: Cessão de Direitos | E4: AFHI12 - AF INVEST CRI FDO. INV. IMOB - RECEBÍVEIS IMOB. | F4: XP INVESTIMENTOS CCTVM S/A | G4: 23 | H4: - | I4: -
A5: Debito | B5: 01/06/2026 | C5: 46174 | D5: Cessão de Direitos - Solicitada | E5: AFHI12 - AF INVEST CRI FDO. INV. IMOB - RECEBÍVEIS IMOB. | F5: XP INVESTIMENTOS CCTVM S/A | G5: 23 | H5: - | I5: -
A6: Debito | B6: 01/06/2026 | C6: 46174 | D6: RESGATE ANTECIPADO/ | E6: CDB - CDB526CSFDK - BANCO DO BRASIL S/A | F6: BANCO DO BRASIL S/A | G6: 5000 | H6: 0.01000032 | I6: 50
A7: Credito | B7: 01/06/2026 | C7: 46174 | D7: APLICAÇÃO | E7: CDB - CDB6260FY9K | F7: BANCO DO BRASIL S/A | G7: 2404334 | H7: 0.01 | I7: 24043.34
A8: Credito | B8: 01/06/2026 | C8: 46174 | D8: Juros Sobre Capital Próprio | E8: ITUB3 - ITAU UNIBANCO HOLDING S.A | F8: XP INVESTIMENTOS CCTVM S/A | G8: 526 | H8: 0.018 | I8: 7.89
A9: Debito | B9: 01/06/2026 | C9: 46174 | D9: Direitos de Subscrição - Não Exercido | E9: PMLL12 - GENIAL MALLS FUNDO DE INVESTIMENTO IMOBILIARIO | F9: XP INVESTIMENTOS CCTVM S/A | G9: 0 | H9: - | I9: -
A10: Credito | B10: 29/05/2026 | C10: 46171 | D10: Direito de Subscrição | E10: HGRU12 - PATRIA RENDA URBANA - FUNDO DE INVESTIMENTO IMOBILIARIO - RE | F10: XP INVESTIMENTOS CCTVM S/A | G10: 64 | H10: - | I10: -
A11: Credito | B11: 29/05/2026 | C11: 46171 | D11: Cessão de Direitos | E11: PMLL12 - GENIAL MALLS FUNDO DE INVESTIMENTO IMOBILIARIO | F11: XP INVESTIMENTOS CCTVM S/A | G11: 93 | H11: - | I11: -
A12: Debito | B12: 29/05/2026 | C12: 46171 | D12: Cessão de Direitos - Solicitada | E12: PMLL12 - GENIAL MALLS FUNDO DE INVESTIMENTO IMOBILIARIO | F12: XP INVESTIMENTOS CCTVM S/A | G12: 93 | H12: - | I12: -
A13: Credito | B13: 28/05/2026 | C13: 46170 | D13: Atualização | E13: PETR4 - PETROLEO BRASILEIRO S/A PETROBRAS | F13: XP INVESTIMENTOS CCTVM S/A | G13: 600 | H13: - | I13: -
A14: Credito | B14: 27/05/2026 | C14: 46169 | D14: APLICAÇÃO | E14: CDB - CDB526CSFDK | F14: BANCO DO BRASIL S/A | G14: 2473459 | H14: 0.01 | I14: 24734.59
A15: Credito | B15: 27/05/2026 | C15: 46169 | D15: Dividendo | E15: LEVE3 - MAHLE-METAL LEVE S.A. | F15: XP INVESTIMENTOS CCTVM S/A | G15: 600 | H15: 0.253 | I15: 152.01
A16: Credito | B16: 27/05/2026 | C16: 46169 | D16: Juros Sobre Capital Próprio | E16: LEVE3 - MAHLE-METAL LEVE S.A. | F16: XP INVESTIMENTOS CCTVM S/A | G16: 300 | H16: 0.206 | I16: 52.57
A17: Credito | B17: 27/05/2026 | C17: 46169 | D17: Dividendo | E17: LEVE3 - MAHLE-METAL LEVE S.A. | F17: XP INVESTIMENTOS CCTVM S/A | G17: 600 | H17: 1.783 | I17: 1069.74
A18: Credito | B18: 27/05/2026 | C18: 46169 | D18: Dividendo | E18: TAEE11 - TRANSMISSORA ALIANCA DE ENERGIA ELETRICA S/A | F18: XP INVESTIMENTOS CCTVM S/A | G18: 700 | H18: 0.153 | I18: 107.44
A19: Credito | B19: 27/05/2026 | C19: 46169 | D19: Dividendo | E19: TAEE11 - TRANSMISSORA ALIANCA DE ENERGIA ELETRICA S/A | F19: XP INVESTIMENTOS CCTVM S/A | G19: 700 | H19: 0.755 | I19: 528.76
A20: Credito | B20: 25/05/2026 | C20: 46167 | D20: Atualização | E20: BBSE3 - BB SEGURIDADE PARTICIPACOES S.A. | F20: XP INVESTIMENTOS CCTVM S/A | G20: 500 | H20: - | I20: -
A21: Credito | B21: 22/05/2026 | C21: 46164 | D21: Rendimento | E21: AFHI11 - AF INVEST CRI FDO. INV. IMOB - RECEBÍVEIS IMOB. | F21: XP INVESTIMENTOS CCTVM S/A | G21: 132 | H21: 1.03 | I21: 135.96
A22: Credito | B22: 20/05/2026 | C22: 46162 | D22: Direito de Subscrição | E22: AFHI12 - AF INVEST CRI FDO. INV. IMOB - RECEBÍVEIS IMOB. | F22: XP INVESTIMENTOS CCTVM S/A | G22: 23 | H22: - | I22: -
A23: Credito | B23: 20/05/2026 | C23: 46162 | D23: Juros Sobre Capital Próprio | E23: EGIE3 - ENGIE BRASIL ENERGIA S.A. | F23: XP INVESTIMENTOS CCTVM S/A | G23: 420 | H23: 0.088 | I23: 31.25
A24: Credito | B24: 20/05/2026 | C24: 46162 | D24: Dividendo | E24: EGIE3 - ENGIE BRASIL ENERGIA S.A. | F24: XP INVESTIMENTOS CCTVM S/A | G24: 620 | H24: 0.488 | I24: 302.73
A25: Credito | B25: 20/05/2026 | C25: 46162 | D25: Juros Sobre Capital Próprio | E25: PETR4 - PETROLEO BRASILEIRO S/A PETROBRAS | F25: XP INVESTIMENTOS CCTVM S/A | G25: 600 | H25: 0.313 | I25: 154.99
A26: Credito | B26: 20/05/2026 | C26: 46162 | D26: Rendimento | E26: PETR4 - PETROLEO BRASILEIRO S/A PETROBRAS | F26: XP INVESTIMENTOS CCTVM S/A | G26: 600 | H26: 0.016 | I26: 7.67
A27: Credito | B27: 19/05/2026 | C27: 46161 | D27: Direito de Subscrição | E27: PMLL12 - GENIAL MALLS FUNDO DE INVESTIMENTO IMOBILIARIO | F27: XP INVESTIMENTOS CCTVM S/A | G27: 93 | H27: - | I27: -
A28: Credito | B28: 18/05/2026 | C28: 46160 | D28: Rendimento | E28: PCIP11 - FDO INV. IMOB. VBI CRI | F28: XP INVESTIMENTOS CCTVM S/A | G28: 147 | H28: 0.89 | I28: 130.83
A29: Credito | B29: 15/05/2026 | C29: 46157 | D29: Dividendo | E29: CXSE3 - CAIXA SEGURIDADE PARTICIPACOES S/A | F29: XP INVESTIMENTOS CCTVM S/A | G29: 1000 | H29: 0.33 | I29: 330
A30: Credito | B30: 15/05/2026 | C30: 46157 | D30: Rendimento | E30: HGLG11 - PÁTRIA LOG - FDO INV IMOB - RESPONSABILIDADE LTDA. | F30: XP INVESTIMENTOS CCTVM S/A | G30: 99 | H30: 1.1 | I30: 108.9
A31: Credito | B31: 15/05/2026 | C31: 46157 | D31: Rendimento | E31: HGRU11 - PATRIA RENDA URBANA - FUNDO DE INVESTIMENTO IMOBILIARIO - RE | F31: XP INVESTIMENTOS CCTVM S/A | G31: 129 | H31: 0.95 | I31: 122.55
A32: Credito | B32: 15/05/2026 | C32: 46157 | D32: Rendimento | E32: PMLL11 - GENIAL MALLS FUNDO DE INVESTIMENTO IMOBILIARIO | F32: XP INVESTIMENTOS CCTVM S/A | G32: 153 | H32: 1 | I32: 153
A33: Credito | B33: 08/05/2026 | C33: 46150 | D33: Rendimento | E33: LVBI11 - FII LVBI VBI | F33: XP INVESTIMENTOS CCTVM S/A | G33: 113 | H33: 0.75 | I33: 84.75
A34: Credito | B34: 08/05/2026 | C34: 46150 | D34: Dividendo | E34: MGLU3 - MAGAZINE LUIZA S.A. | F34: XP INVESTIMENTOS CCTVM S/A | G34: 115 | H34: 0.081 | I34: 9.34
A35: Credito | B35: 05/05/2026 | C35: 46147 | D35: Dividendo | E35: FLRY3 - FLEURY S.A. | F35: XP INVESTIMENTOS CCTVM S/A | G35: 830 | H35: 0.404 | I35: 335.03
A36: Credito | B36: 04/05/2026 | C36: 46146 | D36: Juros Sobre Capital Próprio | E36: ITUB3 - ITAU UNIBANCO HOLDING S.A | F36: XP INVESTIMENTOS CCTVM S/A | G36: 526 | H36: 0.018 | I36: 7.89
A37: Credito | B37: 23/04/2026 | C37: 46135 | D37: Rendimento | E37: AFHI11 - AF INVEST CRI FDO. INV. IMOB - RECEBÍVEIS IMOB. | F37: XP INVESTIMENTOS CCTVM S/A | G37: 132 | H37: 0.98 | I37: 129.36
A38: Credito | B38: 16/04/2026 | C38: 46128 | D38: Rendimento | E38: PCIP11 - FDO INV. IMOB. VBI CRI | F38: XP INVESTIMENTOS CCTVM S/A | G38: 147 | H38: 0.85 | I38: 124.95
A39: Credito | B39: 15/04/2026 | C39: 46127 | D39: Rendimento | E39: HGLG11 - PÁTRIA LOG - FDO INV IMOB - RESPONSABILIDADE LTDA. | F39: XP INVESTIMENTOS CCTVM S/A | G39: 99 | H39: 1.1 | I39: 108.9
... A45: Credito | B45: 25/03/2026 | C45: 46106 | D45: Leilão de Fração | E45: MGLU3 - MAGAZINE LUIZA S.A. | F45: XP INVESTIMENTOS CCTVM S/A | G45: 0.5 | H45: 9.147 | I45: 4.57
A46: Credito | B46: 25/03/2026 | C46: 46106 | D46: Atualização | E46: PETR4 - PETROLEO BRASILEIRO S/A PETROBRAS | F46: XP INVESTIMENTOS CCTVM S/A | G46: 600 | H46: - | I46: -
A47: Credito | B47: 20/03/2026 | C47: 46101 | D47: Rendimento | E47: AFHI11 - AF INVEST CRI FDO. INV. IMOB - RECEBÍVEIS IMOB. | F47: XP INVESTIMENTOS CCTVM S/A | G47: 132 | H47: 0.97 | I47: 128.04
A48: Credito | B48: 20/03/2026 | C48: 46101 | D48: Rendimento | E48: PETR4 - PETROLEO BRASILEIRO S/A PETROBRAS | F48: XP INVESTIMENTOS CCTVM S/A | G48: 500 | H48: 0.009 | I48: 3.47
A49: Credito | B49: 20/03/2026 | C49: 46101 | D49: Dividendo | E49: PETR4 - PETROLEO BRASILEIRO S/A PETROBRAS | F49: XP INVESTIMENTOS CCTVM S/A | G49: 500 | H49: 0.296 | I49: 148.21
A50: Credito | B50: 20/03/2026 | C50: 46101 | D50: Rendimento | E50: PETR4 - PETROLEO BRASILEIRO S/A PETROBRAS | F50: XP INVESTIMENTOS CCTVM S/A | G50: 500 | H50: 0.005 | I50: 2.05
A51: Credito | B51: 20/03/2026 | C51: 46101 | D51: Juros Sobre Capital Próprio | E51: PETR4 - PETROLEO BRASILEIRO S/A PETROBRAS | F51: XP INVESTIMENTOS CCTVM S/A | G51: 500 | H51: 0.175 | I51: 74.46
A52: Debito | B52: 17/03/2026 | C52: 46098 | D52: Direitos de Subscrição - Não Exercido | E52: HYPE1 - HYPERA S.A. | F52: XP INVESTIMENTOS CCTVM S/A | G52: 0 | H52: - | I52: -
A53: Debito | B53: 16/03/2026 | C53: 46097 | D53: Cessão de Direitos - Solicitada | E53: HYPE1 - HYPERA S.A. | F53: XP INVESTIMENTOS CCTVM S/A | G53: 44 | H53: - | I53: -
A54: Credito | B54: 16/03/2026 | C54: 46097 | D54: Cessão de Direitos | E54: HYPE1 - HYPERA S.A. | F54: XP INVESTIMENTOS CCTVM S/A | G54: 44 | H54: - | I54: -
A55: Credito | B55: 16/03/2026 | C55: 46097 | D55: Rendimento | E55: PCIP11 - FDO INV. IMOB. VBI CRI | F55: XP INVESTIMENTOS CCTVM S/A | G55: 147 | H55: 0.8 | I55: 117.6
A56: Credito | B56: 13/03/2026 | C56: 46094 | D56: Rendimento | E56: HGLG11 - PÁTRIA LOG - FDO INV IMOB - RESPONSABILIDADE LTDA. | F56: XP INVESTIMENTOS CCTVM S/A | G56: 99 | H56: 1.1 | I56: 108.9
A57: Credito | B57: 13/03/2026 | C57: 46094 | D57: Rendimento | E57: HGRU11 - PATRIA RENDA URBANA - FUNDO DE INVESTIMENTO IMOBILIARIO - RE | F57: XP INVESTIMENTOS CCTVM S/A | G57: 129 | H57: 0.95 | I57: 122.55
A58: Credito | B58: 13/03/2026 | C58: 46094 | D58: Rendimento | E58: PMLL11 - GENIAL MALLS FUNDO DE INVESTIMENTO IMOBILIARIO | F58: XP INVESTIMENTOS CCTVM S/A | G58: 153 | H58: 1 | I58: 153
A59: Credito | B59: 10/03/2026 | C59: 46091 | D59: Leilão de Fração | E59: ITUB3 - ITAU UNIBANCO HOLDING S.A | F59: XP INVESTIMENTOS CCTVM S/A | G59: 0.6 | H59: 44.873 | I59: 26.92
A60: Credito | B60: 06/03/2026 | C60: 46087 | D60: Juros Sobre Capital Próprio | E60: ITUB3 - ITAU UNIBANCO HOLDING S.A | F60: XP INVESTIMENTOS CCTVM S/A | G60: 220 | H60: 0.37 | I60: 69.14
A61: Credito | B61: 06/03/2026 | C61: 46087 | D61: Rendimento | E61: LVBI11 - FII LVBI VBI | F61: XP INVESTIMENTOS CCTVM S/A | G61: 113 | H61: 0.75 | I61: 84.75
A62: Credito | B62: 04/03/2026 | C62: 46085 | D62: Dividendo | E62: VALE3 - VALE S.A. | F62: XP INVESTIMENTOS CCTVM S/A | G62: 200 | H62: 0.768 | I62: 153.62
A63: Credito | B63: 04/03/2026 | C63: 46085 | D63: Juros Sobre Capital Próprio | E63: VALE3 - VALE S.A. | F63: XP INVESTIMENTOS CCTVM S/A | G63: 200 | H63: 1.57 | I63: 266.82
A64: Credito | B64: 02/03/2026 | C64: 46083 | D64: Dividendo | E64: BBSE3 - BB SEGURIDADE PARTICIPACOES S.A. | F64: XP INVESTIMENTOS CCTVM S/A | G64: 500 | H64: 2.55 | I64: 1274.98
A65: Credito | B65: 02/03/2026 | C65: 46083 | D65: Rendimento | E65: BBSE3 - BB SEGURIDADE PARTICIPACOES S.A. | F65: XP INVESTIMENTOS CCTVM S/A | G65: 500 | H65: 0.057 | I65: 22.03
A66: Debito | B66: 02/03/2026 | C66: 46083 | D66: Direitos de Subscrição - Não Exercido | E66: HGLG12 - PÁTRIA LOG - FDO INV IMOB - RESPONSABILIDADE LTDA. | F66: XP INVESTIMENTOS CCTVM S/A | G66: 0 | H66: - | I66: -
A67: Credito | B67: 02/03/2026 | C67: 46083 | D67: Juros Sobre Capital Próprio | E67: ITUB3 - ITAU UNIBANCO HOLDING S.A | F67: XP INVESTIMENTOS CCTVM S/A | G67: 526 | H67: 0.018 | I67: 7.89
A68: Credito | B68: 02/03/2026 | C68: 46083 | D68: Atualização | E68: PETR4 - PETROLEO BRASILEIRO S/A PETROBRAS | F68: XP INVESTIMENTOS CCTVM S/A | G68: 600 | H68: - | I68: -
A69: Debito | B69: 27/02/2026 | C69: 46080 | D69: Cessão de Direitos - Solicitada | E69: HGLG12 - PÁTRIA LOG - FDO INV IMOB - RESPONSABILIDADE LTDA. | F69: XP INVESTIMENTOS CCTVM S/A | G69: 9 | H69: - | I69: -
A70: Credito | B70: 27/02/2026 | C70: 46080 | D70: Cessão de Direitos | E70: HGLG12 - PÁTRIA LOG - FDO INV IMOB - RESPONSABILIDADE LTDA. | F70: XP INVESTIMENTOS CCTVM S/A | G70: 9 | H70: - | I70: -
A71: Debito | B71: 25/02/2026 | C71: 46078 | D71: Transferência - Liquidação | E71: VALE3 - VALE S.A. | F71: XP INVESTIMENTOS CCTVM S/A | G71: 200 | H71: 87.99 | I71: 17598
A72: Credito | B72: 24/02/2026 | C72: 46077 | D72: Rendimento | E72: AFHI11 - AF INVEST CRI FDO. INV. IMOB - RECEBÍVEIS IMOB. | F72: XP INVESTIMENTOS CCTVM S/A | G72: 132 | H72: 0.97 | I72: 128.04
A73: Credito | B73: 20/02/2026 | C73: 46073 | D73: Rendimento | E73: PETR4 - PETROLEO BRASILEIRO S/A PETROBRAS | F73: XP INVESTIMENTOS CCTVM S/A | G73: 500 | H73: 0.009 | I73: 3.46
A74: Credito | B74: 20/02/2026 | C74: 46073 | D74: Juros Sobre Capital Próprio | E74: PETR4 - PETROLEO BRASILEIRO S/A PETROBRAS | F74: XP INVESTIMENTOS CCTVM S/A | G74: 500 | H74: 0.472 | I74: 200.43
A75: Credito | B75: 19/02/2026 | C75: 46072 | D75: Atualização | E75: VALE3 - VALE S.A. | F75: XP INVESTIMENTOS CCTVM S/A | G75: 200 | H75: - | I75: -
A76: Credito | B76: 18/02/2026 | C76: 46071 | D76: PAGAMENTO DE JUROS | E76: CRI - 22B0004808 - RIZA SECURITIZADORA S.A. | F76: INTER DISTRIBUIDORA DE TITULOS E VALORES MOBILIARIOS LTDA | G76: 7 | H76: 38.34 | I76: 268.38
A77: Credito | B77: 18/02/2026 | C77: 46071 | D77: Rendimento | E77: PCIP11 - FDO INV. IMOB. VBI CRI | F77: XP INVESTIMENTOS CCTVM S/A | G77: 147 | H77: 0.83 | I77: 122.01
A78: Credito | B78: 13/02/2026 | C78: 46066 | D78: Rendimento | E78: HGLG11 - PÁTRIA LOG - FDO INV IMOB - RESPONSABILIDADE LTDA. | F78: XP INVESTIMENTOS CCTVM S/A | G78: 99 | H78: 1.1 | I78: 108.9
A79: Credito | B79: 13/02/2026 | C79: 46066 | D79: Rendimento | E79: HGRU11 - PATRIA RENDA URBANA - FUNDO DE INVESTIMENTO IMOBILIARIO - RE | F79: XP INVESTIMENTOS CCTVM S/A | G79: 129 | H79: 0.95 | I79: 122.55
A80: Credito | B80: 13/02/2026 | C80: 46066 | D80: Rendimento | E80: PMLL11 - GENIAL MALLS FUNDO DE INVESTIMENTO IMOBILIARIO | F80: XP INVESTIMENTOS CCTVM S/A | G80: 153 | H80: 1 | I80: 153
A81: Credito | B81: 12/02/2026 | C81: 46065 | D81: Direito de Subscrição | E81: HGLG12 - PÁTRIA LOG - FDO INV IMOB - RESPONSABILIDADE LTDA. | F81: XP INVESTIMENTOS CCTVM S/A | G81: 9 | H81: - | I81: -
A82: Credito | B82: 10/02/2026 | C82: 46063 | D82: Direito de Subscrição | E82: HYPE1 - HYPERA S.A. | F82: XP INVESTIMENTOS CCTVM S/A | G82: 44 | H82: - | I82: -
A83: Debito | B83: 09/02/2026 | C83: 46062 | D83: Fração em Ativos | E83: MGLU3 - MAGAZINE LUIZA S.A. | F83: XP INVESTIMENTOS CCTVM S/A | G83: 0.5 | H83: - | I83: -
A84: Credito | B84: 06/02/2026 | C84: 46059 | D84: Rendimento | E84: LVBI11 - FII LVBI VBI | F84: XP INVESTIMENTOS CCTVM S/A | G84: 113 | H84: 0.75 | I84: 84.75
A85: Debito | B85: 03/02/2026 | C85: 46056 | D85: Fração em Ativos | E85: ITUB3 - ITAU UNIBANCO HOLDING S.A | F85: XP INVESTIMENTOS CCTVM S/A | G85: 0.6 | H85: - | I85: -
A86: Credito | B86: 02/02/2026 | C86: 46055 | D86: Juros Sobre Capital Próprio | E86: ITUB3 - ITAU UNIBANCO HOLDING S.A | F86: XP INVESTIMENTOS CCTVM S/A | G86: 326.6 | H86: 0.018 | I86: 4.9
A87: Credito | B87: 28/01/2026 | C87: 46050 | D87: Juros Sobre Capital Próprio | E87: TAEE11 - TRANSMISSORA ALIANCA DE ENERGIA ELETRICA S/A | F87: XP INVESTIMENTOS CCTVM S/A | G87: 700 | H87: 0.419 | I87: 249.55
A88: Credito | B88: 28/01/2026 | C88: 46050 | D88: Dividendo | E88: TAEE11 - TRANSMISSORA ALIANCA DE ENERGIA ELETRICA S/A | F88: XP INVESTIMENTOS CCTVM S/A | G88: 700 | H88: 0.519 | I88: 363.26
A89: Credito | B89: 28/01/2026 | C89: 46050 | D89: Compra | E89: Tesouro IPCA+ 2050 | F89: INTER DISTRIBUIDORA DE TITULOS E VALORES MOBILIARIOS LTDA | G89: 25.37 | H89: 906.25 | I89: 22991.82
A90: Credito | B90: 27/01/2026 | C90: 46049 | D90: Transferência - Liquidação | E90: AFHI11 - AF INVEST CRI FDO. INV. IMOB - RECEBÍVEIS IMOB. | F90: XP INVESTIMENTOS CCTVM S/A | G90: 26 | H90: 95.588 | I90: 2485.29
A91: Credito | B91: 27/01/2026 | C91: 46049 | D91: Transferência - Liquidação | E91: BBSE3 - BB SEGURIDADE PARTICIPACOES S.A. | F91: XP INVESTIMENTOS CCTVM S/A | G91: 100 | H91: 36.55 | I91: 3655
A92: Credito | B92: 27/01/2026 | C92: 46049 | D92: Transferência - Liquidação | E92: CXSE3 - CAIXA SEGURIDADE PARTICIPACOES S/A | F92: XP INVESTIMENTOS CCTVM S/A | G92: 400 | H92: 16.948 | I92: 6779.2
A93: Credito | B93: 27/01/2026 | C93: 46049 | D93: Transferência - Liquidação | E93: ITUB3 - ITAU UNIBANCO HOLDING S.A | F93: XP INVESTIMENTOS CCTVM S/A | G93: 100 | H93: 40.16 | I93: 4016
A94: Credito | B94: 27/01/2026 | C94: 46049 | D94: Transferência - Liquidação | E94: LEVE3 - MAHLE-METAL LEVE S.A. | F94: XP INVESTIMENTOS CCTVM S/A | G94: 100 | H94: 33.89 | I94: 3389
A95: Credito | B95: 27/01/2026 | C95: 46049 | D95: Transferência - Liquidação | E95: LVBI11 - FII LVBI VBI | F95: XP INVESTIMENTOS CCTVM S/A | G95: 21 | H95: 111.63 | I95: 2344.23
A96: Credito | B96: 27/01/2026 | C96: 46049 | D96: Transferência - Liquidação | E96: PCIP11 - FDO INV. IMOB. VBI CRI | F96: XP INVESTIMENTOS CCTVM S/A | G96: 26 | H96: 86.09 | I96: 2238.34
A97: Credito | B97: 22/01/2026 | C97: 46044 | D97: Rendimento | E97: AFHI11 - AF INVEST CRI FDO. INV. IMOB - RECEBÍVEIS IMOB. | F97: XP INVESTIMENTOS CCTVM S/A | G97: 106 | H97: 1.01 | I97: 107.06
... A119: Credito | B119: 02/01/2026 | C119: 46024 | D119: Juros Sobre Capital Próprio | E119: ITUB3 - ITAU UNIBANCO HOLDING S.A | F119: XP INVESTIMENTOS CCTVM S/A | G119: 220 | H119: 0.018 | I119: 3.3
A120: Credito | B120: 02/01/2026 | C120: 46024 | D120: Bonificação em Ativos | E120: MGLU3 - MAGAZINE LUIZA S.A. | F120: XP INVESTIMENTOS CCTVM S/A | G120: 5.5 | H120: - | I120: -
A121: Credito | B121: 30/12/2025 | C121: 46021 | D121: Transferência - Liquidação | E121: AFHI11 - AF INVEST CRI FDO. INV. IMOB - RECEBÍVEIS IMOB. | F121: XP INVESTIMENTOS CCTVM S/A | G121: 76 | H121: 95.37 | I121: 7248.12
A122: Debito | B122: 30/12/2025 | C122: 46021 | D122: Transferência - Liquidação | E122: B3SA3 - B3 S.A. - BRASIL, BOLSA, BALCÃO | F122: XP INVESTIMENTOS CCTVM S/A | G122: 300 | H122: 13.6 | I122: 4080
A123: Debito | B123: 30/12/2025 | C123: 46021 | D123: Transferência - Liquidação | E123: BBAS3 - BANCO DO BRASIL S/A | F123: XP INVESTIMENTOS CCTVM S/A | G123: 300 | H123: 21.67 | I123: 6501
A124: Credito | B124: 30/12/2025 | C124: 46021 | D124: Transferência - Liquidação | E124: BBSE3 - BB SEGURIDADE PARTICIPACOES S.A. | F124: XP INVESTIMENTOS CCTVM S/A | G124: 200 | H124: 35.62 | I124: 7124
A125: Credito | B125: 30/12/2025 | C125: 46021 | D125: Transferência - Liquidação | E125: CXSE3 - CAIXA SEGURIDADE PARTICIPACOES S/A | F125: XP INVESTIMENTOS CCTVM S/A | G125: 300 | H125: 16.4 | I125: 4920
A126: Credito | B126: 30/12/2025 | C126: 46021 | D126: Transferência - Liquidação | E126: EGIE3 - ENGIE BRASIL ENERGIA S.A. | F126: XP INVESTIMENTOS CCTVM S/A | G126: 200 | H126: 31.145 | I126: 6229
...

Sheet Sheet2
A1: Movimentação | B1: nº ocorrencias | C1: descrição | F1: 1 | G1: 2 | H1: 3 | I1: 4 | J1: 5 | K1: 6 | L1: 7 | M1: 8 | N1: 9
F2: Entrada/Saída | G2: Data | H2: Data | I2: Movimentação | J2: Produto | K2: Instituição | L2: Quantidade | M2: Preço unitário | N2: Valor da Operação
A3: Rendimento | B3: =COUNTIF(Movimentação!D:D,A3) -> 587 | C3: rendimentos de FIIs | D3: =MATCH(A3,Movimentação!D:D,0) -> 21 | F3: =INDEX(Movimentação!$A:$I,$D3,F$1) -> Credito | G3: =INDEX(Movimentação!$A:$I,$D3,G$1) -> 22/05/2026 | H3: =INDEX(Movimentação!$A:$I,$D3,H$1) -> 46164 | I3: =INDEX(Movimentação!$A:$I,$D3,I$1) -> Rendimento | J3: =INDEX(Movimentação!$A:$I,$D3,J$1) -> AFHI11 - AF INVEST CRI FDO. INV. IMOB - RECEBÍVEIS IMOB. | K3: =INDEX(Movimentação!$A:$I,$D3,K$1) -> XP INVESTIMENTOS CCTVM S/A | L3: =INDEX(Movimentação!$A:$I,$D3,L$1) -> 132 | M3: =INDEX(Movimentação!$A:$I,$D3,M$1) -> 1.03 | N3: =INDEX(Movimentação!$A:$I,$D3,N$1) -> 135.96
A4: Juros Sobre Capital Próprio | B4: =COUNTIF(Movimentação!D:D,A4) -> 302 | C4: jcp de empresas listadas na B3 | D4: =MATCH(A4,Movimentação!D:D,0) -> 8 | F4: =INDEX(Movimentação!$A:$I,$D4,F$1) -> Credito | G4: =INDEX(Movimentação!$A:$I,$D4,G$1) -> 01/06/2026 | H4: =INDEX(Movimentação!$A:$I,$D4,H$1) -> 46174 | I4: =INDEX(Movimentação!$A:$I,$D4,I$1) -> Juros Sobre Capital Próprio | J4: =INDEX(Movimentação!$A:$I,$D4,J$1) -> ITUB3 - ITAU UNIBANCO HOLDING S.A | K4: =INDEX(Movimentação!$A:$I,$D4,K$1) -> XP INVESTIMENTOS CCTVM S/A | L4: =INDEX(Movimentação!$A:$I,$D4,L$1) -> 526 | M4: =INDEX(Movimentação!$A:$I,$D4,M$1) -> 0.018 | N4: =INDEX(Movimentação!$A:$I,$D4,N$1) -> 7.89
A5: Dividendo | B5: =COUNTIF(Movimentação!D:D,A5) -> 207 | C5: Dividendo de empresas listadas na B3 | D5: =MATCH(A5,Movimentação!D:D,0) -> 15 | F5: =INDEX(Movimentação!$A:$I,$D5,F$1) -> Credito | G5: =INDEX(Movimentação!$A:$I,$D5,G$1) -> 27/05/2026 | H5: =INDEX(Movimentação!$A:$I,$D5,H$1) -> 46169 | I5: =INDEX(Movimentação!$A:$I,$D5,I$1) -> Dividendo | J5: =INDEX(Movimentação!$A:$I,$D5,J$1) -> LEVE3 - MAHLE-METAL LEVE S.A. | K5: =INDEX(Movimentação!$A:$I,$D5,K$1) -> XP INVESTIMENTOS CCTVM S/A | L5: =INDEX(Movimentação!$A:$I,$D5,L$1) -> 600 | M5: =INDEX(Movimentação!$A:$I,$D5,M$1) -> 0.253 | N5: =INDEX(Movimentação!$A:$I,$D5,N$1) -> 152.01
A6: Transferência - Liquidação | B6: =COUNTIF(Movimentação!D:D,A6) -> 181 | C6: venda de ativos listados na b3. Ignorar. Usar o arquivo de negociações | D6: =MATCH(A6,Movimentação!D:D,0) -> 71 | F6: =INDEX(Movimentação!$A:$I,$D6,F$1) -> Debito | G6: =INDEX(Movimentação!$A:$I,$D6,G$1) -> 25/02/2026 | H6: =INDEX(Movimentação!$A:$I,$D6,H$1) -> 46078 | I6: =INDEX(Movimentação!$A:$I,$D6,I$1) -> Transferência - Liquidação | J6: =INDEX(Movimentação!$A:$I,$D6,J$1) -> VALE3 - VALE S.A. | K6: =INDEX(Movimentação!$A:$I,$D6,K$1) -> XP INVESTIMENTOS CCTVM S/A | L6: =INDEX(Movimentação!$A:$I,$D6,L$1) -> 200 | M6: =INDEX(Movimentação!$A:$I,$D6,M$1) -> 87.99 | N6: =INDEX(Movimentação!$A:$I,$D6,N$1) -> 17598
A7: Transferência | B7: =COUNTIF(Movimentação!D:D,A7) -> 81 | C7: transferencia de ativos entre corretoras. Deve ser tratado em pares, entre transações que ocorrem com o mesmo ativo no mesmo dia | D7: =MATCH(A7,Movimentação!D:D,0) -> 304 | F7: =INDEX(Movimentação!$A:$I,$D7,F$1) -> Credito | G7: =INDEX(Movimentação!$A:$I,$D7,G$1) -> 14/02/2025 | H7: =INDEX(Movimentação!$A:$I,$D7,H$1) -> 45702 | I7: =INDEX(Movimentação!$A:$I,$D7,I$1) -> Transferência | J7: =INDEX(Movimentação!$A:$I,$D7,J$1) -> B3SA3 - B3 S.A. - BRASIL, BOLSA, BALCÃO | K7: =INDEX(Movimentação!$A:$I,$D7,K$1) -> XP INVESTIMENTOS CCTVM S/A | L7: =INDEX(Movimentação!$A:$I,$D7,L$1) -> 700 | M7: =INDEX(Movimentação!$A:$I,$D7,M$1) -> - | N7: =INDEX(Movimentação!$A:$I,$D7,N$1) -> -
A8: Juros Sobre Capital Próprio - Transferido | B8: =COUNTIF(Movimentação!D:D,A8) -> 44 | C8: transferencia de JCP entre corretoras. Deve ser tratado em pares, entre transações que ocorrem com o mesmo ativo no mesmo dia | D8: =MATCH(A8,Movimentação!D:D,0) -> 312 | F8: =INDEX(Movimentação!$A:$I,$D8,F$1) -> Credito | G8: =INDEX(Movimentação!$A:$I,$D8,G$1) -> 14/02/2025 | H8: =INDEX(Movimentação!$A:$I,$D8,H$1) -> 45702 | I8: =INDEX(Movimentação!$A:$I,$D8,I$1) -> Juros Sobre Capital Próprio - Transferido | J8: =INDEX(Movimentação!$A:$I,$D8,J$1) -> ETER3 - ETERNIT S.A. | K8: =INDEX(Movimentação!$A:$I,$D8,K$1) -> XP INVESTIMENTOS CCTVM S/A | L8: =INDEX(Movimentação!$A:$I,$D8,L$1) -> 500 | M8: =INDEX(Movimentação!$A:$I,$D8,M$1) -> 0.052 | N8: =INDEX(Movimentação!$A:$I,$D8,N$1) -> 22.11
A9: Atualização | B9: =COUNTIF(Movimentação!D:D,A9) -> 39 | C9: ignorar | D9: =MATCH(A9,Movimentação!D:D,0) -> 13 | F9: =INDEX(Movimentação!$A:$I,$D9,F$1) -> Credito | G9: =INDEX(Movimentação!$A:$I,$D9,G$1) -> 28/05/2026 | H9: =INDEX(Movimentação!$A:$I,$D9,H$1) -> 46170 | I9: =INDEX(Movimentação!$A:$I,$D9,I$1) -> Atualização | J9: =INDEX(Movimentação!$A:$I,$D9,J$1) -> PETR4 - PETROLEO BRASILEIRO S/A PETROBRAS | K9: =INDEX(Movimentação!$A:$I,$D9,K$1) -> XP INVESTIMENTOS CCTVM S/A | L9: =INDEX(Movimentação!$A:$I,$D9,L$1) -> 600 | M9: =INDEX(Movimentação!$A:$I,$D9,M$1) -> - | N9: =INDEX(Movimentação!$A:$I,$D9,N$1) -> -
A10: Direito de Subscrição | B10: =COUNTIF(Movimentação!D:D,A10) -> 35 | C10: ignorar | D10: =MATCH(A10,Movimentação!D:D,0) -> 10 | F10: =INDEX(Movimentação!$A:$I,$D10,F$1) -> Credito | G10: =INDEX(Movimentação!$A:$I,$D10,G$1) -> 29/05/2026 | H10: =INDEX(Movimentação!$A:$I,$D10,H$1) -> 46171 | I10: =INDEX(Movimentação!$A:$I,$D10,I$1) -> Direito de Subscrição | J10: =INDEX(Movimentação!$A:$I,$D10,J$1) -> HGRU12 - PATRIA RENDA URBANA - FUNDO DE INVESTIMENTO IMOBILIARIO - RE | K10: =INDEX(Movimentação!$A:$I,$D10,K$1) -> XP INVESTIMENTOS CCTVM S/A | L10: =INDEX(Movimentação!$A:$I,$D10,L$1) -> 64 | M10: =INDEX(Movimentação!$A:$I,$D10,M$1) -> - | N10: =INDEX(Movimentação!$A:$I,$D10,N$1) -> -
A11: Direitos de Subscrição - Não Exercido | B11: =COUNTIF(Movimentação!D:D,A11) -> 34 | C11: ignorar | D11: =MATCH(A11,Movimentação!D:D,0) -> 3 | F11: =INDEX(Movimentação!$A:$I,$D11,F$1) -> Debito | G11: =INDEX(Movimentação!$A:$I,$D11,G$1) -> 02/06/2026 | H11: =INDEX(Movimentação!$A:$I,$D11,H$1) -> 46175 | I11: =INDEX(Movimentação!$A:$I,$D11,I$1) -> Direitos de Subscrição - Não Exercido | J11: =INDEX(Movimentação!$A:$I,$D11,J$1) -> AFHI12 - AF INVEST CRI FDO. INV. IMOB - RECEBÍVEIS IMOB. | K11: =INDEX(Movimentação!$A:$I,$D11,K$1) -> XP INVESTIMENTOS CCTVM S/A | L11: =INDEX(Movimentação!$A:$I,$D11,L$1) -> 0 | M11: =INDEX(Movimentação!$A:$I,$D11,M$1) -> - | N11: =INDEX(Movimentação!$A:$I,$D11,N$1) -> -
A12: Cessão de Direitos | B12: =COUNTIF(Movimentação!D:D,A12) -> 20 | C12: ignorar | D12: =MATCH(A12,Movimentação!D:D,0) -> 4 | F12: =INDEX(Movimentação!$A:$I,$D12,F$1) -> Credito | G12: =INDEX(Movimentação!$A:$I,$D12,G$1) -> 01/06/2026 | H12: =INDEX(Movimentação!$A:$I,$D12,H$1) -> 46174 | I12: =INDEX(Movimentação!$A:$I,$D12,I$1) -> Cessão de Direitos | J12: =INDEX(Movimentação!$A:$I,$D12,J$1) -> AFHI12 - AF INVEST CRI FDO. INV. IMOB - RECEBÍVEIS IMOB. | K12: =INDEX(Movimentação!$A:$I,$D12,K$1) -> XP INVESTIMENTOS CCTVM S/A | L12: =INDEX(Movimentação!$A:$I,$D12,L$1) -> 23 | M12: =INDEX(Movimentação!$A:$I,$D12,M$1) -> - | N12: =INDEX(Movimentação!$A:$I,$D12,N$1) -> -
A13: Cessão de Direitos - Solicitada | B13: =COUNTIF(Movimentação!D:D,A13) -> 20 | C13: ignorar | D13: =MATCH(A13,Movimentação!D:D,0) -> 5 | F13: =INDEX(Movimentação!$A:$I,$D13,F$1) -> Debito | G13: =INDEX(Movimentação!$A:$I,$D13,G$1) -> 01/06/2026 | H13: =INDEX(Movimentação!$A:$I,$D13,H$1) -> 46174 | I13: =INDEX(Movimentação!$A:$I,$D13,I$1) -> Cessão de Direitos - Solicitada | J13: =INDEX(Movimentação!$A:$I,$D13,J$1) -> AFHI12 - AF INVEST CRI FDO. INV. IMOB - RECEBÍVEIS IMOB. | K13: =INDEX(Movimentação!$A:$I,$D13,K$1) -> XP INVESTIMENTOS CCTVM S/A | L13: =INDEX(Movimentação!$A:$I,$D13,L$1) -> 23 | M13: =INDEX(Movimentação!$A:$I,$D13,M$1) -> - | N13: =INDEX(Movimentação!$A:$I,$D13,N$1) -> -
A14: Recibo de Subscrição | B14: =COUNTIF(Movimentação!D:D,A14) -> 18 | C14: ignorar | D14: =MATCH(A14,Movimentação!D:D,0) -> 1240 | F14: =INDEX(Movimentação!$A:$I,$D14,F$1) -> Credito | G14: =INDEX(Movimentação!$A:$I,$D14,G$1) -> 17/08/2021 | H14: =INDEX(Movimentação!$A:$I,$D14,H$1) -> 44425 | I14: =INDEX(Movimentação!$A:$I,$D14,I$1) -> Recibo de Subscrição | J14: =INDEX(Movimentação!$A:$I,$D14,J$1) -> XPML13 - XP MALLS FDO INV IMOB FII | K14: =INDEX(Movimentação!$A:$I,$D14,K$1) -> MODAL DTVM LTDA | L14: =INDEX(Movimentação!$A:$I,$D14,L$1) -> 8 | M14: =INDEX(Movimentação!$A:$I,$D14,M$1) -> - | N14: =INDEX(Movimentação!$A:$I,$D14,N$1) -> -
... A34: Incorporação | B34: =COUNTIF(Movimentação!D:D,A34) -> 1 | C34: ignorar | D34: =MATCH(A34,Movimentação!D:D,0) -> 1190 | F34: =INDEX(Movimentação!$A:$I,$D34,F$1) -> Credito | G34: =INDEX(Movimentação!$A:$I,$D34,G$1) -> 05/10/2021 | H34: =INDEX(Movimentação!$A:$I,$D34,H$1) -> 44474 | I34: =INDEX(Movimentação!$A:$I,$D34,I$1) -> Incorporação | J34: =INDEX(Movimentação!$A:$I,$D34,J$1) -> XPBR31 - XP INC. | K34: =INDEX(Movimentação!$A:$I,$D34,K$1) -> MODAL DTVM LTDA | L34: =INDEX(Movimentação!$A:$I,$D34,L$1) -> 6.92 | M34: =INDEX(Movimentação!$A:$I,$D34,M$1) -> - | N34: =INDEX(Movimentação!$A:$I,$D34,N$1) -> -
